fstpy/__init__.py
fstpy/authorizers.py
fstpy/filesystems.py
fstpy-0.1.1.data/scripts/fstpyd
fstpy-0.1.1.dist-info/LICENSE
fstpy-0.1.1.dist-info/METADATA
fstpy-0.1.1.dist-info/WHEEL
fstpy-0.1.1.dist-info/top_level.txt
fstpy-0.1.1.dist-info/RECORD
