Metadata-Version: 2.1
Name: fstpy
Version: 0.1.1
Summary: Bridging FTP and cloud storage
Home-page: https://github.com/desmoteo/FsTPy
Author: Matteo Ferrabone
Author-email: matteo.ferrabone@gmail.com
License: MIT
Platform: UNKNOWN
Classifier: Programming Language :: Python :: 3
Classifier: License :: OSI Approved :: MIT License
Classifier: Operating System :: OS Independent
Classifier: Intended Audience :: Developers
Classifier: Intended Audience :: System Administrators
Classifier: Intended Audience :: Information Technology
Classifier: Topic :: Internet :: File Transfer Protocol (FTP)
Classifier: Topic :: Software Development :: Libraries :: Python Modules
Classifier: Topic :: System :: Filesystems
Classifier: Topic :: Utilities 
Classifier: Topic :: System
Classifier: Topic :: System :: Archiving
Classifier: Topic :: Internet :: File Transfer Protocol (FTP)
Requires-Python: >=3.6
Requires-Dist: begins
Requires-Dist: fs
Requires-Dist: pyftpdlib
Requires-Dist: pyopenssl
Requires-Dist: zmq
